fiche/__init__.py
fiche/cli.py
fiche/cons.py
fiche/data.py
fiche/fiche_config.yaml
fiche/observer_mode.py
fiche/orm.py
fiche/service.py
fiche/util.py
fiche/test/test_cons.py
fiche/test/test_fichedata.py
fiche/test/test_mongo_manager.py
fiche/test/test_observer_mode.py
shihua_fiche-0.1.dist-info/LICENSE
shihua_fiche-0.1.dist-info/METADATA
shihua_fiche-0.1.dist-info/WHEEL
shihua_fiche-0.1.dist-info/entry_points.txt
shihua_fiche-0.1.dist-info/top_level.txt
shihua_fiche-0.1.dist-info/RECORD
