Metadata-Version: 2.1
Name: shihua-fiche
Version: 0.1
Summary: Fiche is a metadata management tool with MongoDB about algorithm info,model info,parameter info,application info,dataset info and more;supporting http interface and python sdk.
Home-page: https://github.com/redblue0216/Fiche
Author: shihua
Author-email: 15021408795@163.com
License: MIT
Platform: UNKNOWN
Requires-Python: >=3.9.12
License-File: LICENSE
